aiostep/__init__.py
aiostep/asyncio/__init__.py
aiostep/asyncio/base.py
aiostep/asyncio/file.py
aiostep/asyncio/memory.py
aiostep/asyncio/redis.py
aiostep/steps/__init__.py
aiostep/steps/dialects/aiogram_dialect.py
aiostep/steps/dialects/telebot_dialect.py
aiostep/steps/dialects/telethon_dialect.py
aiostep/steps/functions.py
aiostep/storage/__init__.py
aiostep/storage/base.py
aiostep/storage/file.py
aiostep/storage/memory.py
aiostep/storage/redis.py
aiostep/utils.py
aiostep-0.3.6.dist-info/licenses/LICENSE
aiostep-0.3.6.dist-info/METADATA
aiostep-0.3.6.dist-info/WHEEL
aiostep-0.3.6.dist-info/RECORD
