Metadata-Version: 2.4
Name: aiostep
Version: 0.3.6
Summary: A Python library to handle steps in aiogram framework.
License: MIT
License-File: LICENSE
Keywords: aiogram,steps,states,Telegram bot,asynchronous,aiostep,telebot,telethon
Author: Nasrollah Yusefi
Requires-Python: >=3.9,<4.0
Classifier: License :: OSI Approved :: MIT License
Classifier: Programming Language :: Python :: 3
Classifier: Programming Language :: Python :: 3.9
Classifier: Programming Language :: Python :: 3.10
Classifier: Programming Language :: Python :: 3.11
Classifier: Programming Language :: Python :: 3.12
Classifier: Programming Language :: Python :: 3.13
Classifier: Programming Language :: Python :: 3.14
Provides-Extra: redis
Requires-Dist: cachebox (>=4.2.3,<5.0.0)
Requires-Dist: msgspec (>=0.19.0,<0.20.0)
Requires-Dist: qsave (>=1.1.1,<2.0.0)
Requires-Dist: redis (>=5.1.1,<6.0.0) ; extra == "redis"
Project-URL: Homepage, https://github.com/NasrollahYusefi/aiostep
